generic_utility/__init__.py
generic_utility/utils.py
shautoserv-0.1.1.dist-info/METADATA
shautoserv-0.1.1.dist-info/WHEEL
shautoserv-0.1.1.dist-info/top_level.txt
shautoserv-0.1.1.dist-info/RECORD
