Metadata-Version: 2.4
Name: SHautoserv
Version: 0.1.1
Summary: Reusable automation utilities for SmartHub services
Author-email: Mohamed Elhaj-Abdou <mohamedelsayedmohammed.2020@gmail.com>
License: MIT
Requires-Python: >=3.7
Requires-Dist: pandas
Requires-Dist: numpy
Requires-Dist: requests
Requires-Dist: lxml
Requires-Dist: pillow
Requires-Dist: mss
Requires-Dist: pyautogui
Requires-Dist: selenium
Requires-Dist: webdriver-manager
Requires-Dist: google-auth-oauthlib
Requires-Dist: google-api-python-client
